CAT/__init__.py
CAT/dataset/__init__.py
CAT/dataset/adaptest_dataset.py
CAT/dataset/dataset.py
CAT/dataset/train_dataset.py
CAT/model/IRT.py
CAT/model/NCD.py
CAT/model/__init__.py
CAT/model/abstract_model.py
CAT/model/utils.py
CAT/strategy/BECAT_strategy.py
CAT/strategy/BOBCAT_strategy.py
CAT/strategy/KLI_strategy.py
CAT/strategy/MAAT_strategy.py
CAT/strategy/MFI_strategy.py
CAT/strategy/NCAT_strategy.py
CAT/strategy/__init__.py
CAT/strategy/abstract_strategy.py
CAT/strategy/random_strategy.py
EduCAT-0.0.1.dist-info/LICENSE
EduCAT-0.0.1.dist-info/METADATA
EduCAT-0.0.1.dist-info/WHEEL
EduCAT-0.0.1.dist-info/top_level.txt
EduCAT-0.0.1.dist-info/RECORD
