Metadata-Version: 2.1
Name: EduCAT
Version: 0.0.1
Summary: A CAT Framework 
Home-page: https://github.com/bigdata-ustc/CAT
Author: Yuting Ning
Author-email: ningyt@mail.ustc.edu.cn
Classifier: Programming Language :: Python :: 3
License-File: LICENSE
Requires-Dist: torch
Requires-Dist: vegas
Requires-Dist: numpy
Requires-Dist: scikit-learn
Requires-Dist: scipy
